titus_isolate/__init__.py
titus_isolate/constants.py
titus_isolate/exit_handler.py
titus_isolate/real_exit_handler.py
titus_isolate/utils.py
titus_isolate/allocate/__init__.py
titus_isolate/allocate/allocate_request.py
titus_isolate/allocate/allocate_response.py
titus_isolate/allocate/allocate_threads_request.py
titus_isolate/allocate/constants.py
titus_isolate/allocate/cpu_allocate_exception.py
titus_isolate/allocate/cpu_allocator.py
titus_isolate/allocate/fall_back_cpu_allocator.py
titus_isolate/allocate/forecast_ip_cpu_allocator.py
titus_isolate/allocate/greedy_cpu_allocator.py
titus_isolate/allocate/integer_program_cpu_allocator.py
titus_isolate/allocate/naive_cpu_allocator.py
titus_isolate/allocate/noop_allocator.py
titus_isolate/allocate/noop_reset_allocator.py
titus_isolate/allocate/remote_cpu_allocator.py
titus_isolate/allocate/utils.py
titus_isolate/api/__init__.py
titus_isolate/api/solve.py
titus_isolate/api/status.py
titus_isolate/api/testing.py
titus_isolate/cgroup/__init__.py
titus_isolate/cgroup/cgroup_manager.py
titus_isolate/cgroup/file_cgroup_manager.py
titus_isolate/cgroup/utils.py
titus_isolate/config/__init__.py
titus_isolate/config/agent_property_provider.py
titus_isolate/config/config_manager.py
titus_isolate/config/constants.py
titus_isolate/config/env_property_provider.py
titus_isolate/config/property_provider.py
titus_isolate/config/restart_property_watcher.py
titus_isolate/config/utils.py
titus_isolate/event/__init__.py
titus_isolate/event/constants.py
titus_isolate/event/create_event_handler.py
titus_isolate/event/event_handler.py
titus_isolate/event/event_manager.py
titus_isolate/event/free_event_handler.py
titus_isolate/event/rebalance_event_handler.py
titus_isolate/event/reconcile_event_handler.py
titus_isolate/event/utils.py
titus_isolate/isolate/__init__.py
titus_isolate/isolate/balance.py
titus_isolate/isolate/detect.py
titus_isolate/isolate/metrics_utils.py
titus_isolate/isolate/reconciler.py
titus_isolate/isolate/update.py
titus_isolate-20190718.0.0.dist-info/METADATA
titus_isolate-20190718.0.0.dist-info/WHEEL
titus_isolate-20190718.0.0.dist-info/top_level.txt
titus_isolate-20190718.0.0.dist-info/RECORD
