Metadata-Version: 2.1
Name: titus-isolate
Version: 20190718.0.0
Summary: Isolate containers running on Titus
Home-page: https://github.com/Netflix-Skunkworks/titus-isolate
Maintainer: Gabriel Hartmann
Maintainer-email: ghartmann@netflix.com
License: UNKNOWN
Platform: UNKNOWN
